{
  "products": [
    {
      "sku": "0200MD",
      "category": "BABUCHAS",
      "name": "Babucha Modal",
      "fabric": "Modal con Lycra",
      "sizes": ["8", "10", "12", "14", "16"],
      "wholesalePrice": 8500,
      "retailPrice": 8500,
      "colors": ["Negro", "Gris Noche", "Verde Musgo", "Gris", "Uva"],
      "image": "0200MD-Babucha Modal/DSC_0033.jpg",
      "description": "Comodidad absoluta para tu día a día. Tela suave que acompaña tus curvas con elegancia."
    },
    {
      "sku": "0302BE",
      "category": "BLAZERS",
      "name": "Blazer Golden",
      "fabric": "Bengalina",
      "sizes": ["6", "8", "25"],
      "wholesalePrice": 13500,
      "retailPrice": 13500,
      "colors": ["Negro", "Verde Militar", "Verde Esmeralda"],
      "image": "0302BE-Blazer Golden/blazergolden.jpg",
      "description": "Elegancia que impone presencia. El blazer perfecto para ocasiones especiales o el día a día con actitud."
    },
    {
      "sku": "0401LU",
      "category": "BLUSAS",
      "name": "Blusa Cruzada Lurex",
      "fabric": "Lurex",
      "sizes": ["8", "10", "12", "14"],
      "wholesalePrice": 26000,
      "retailPrice": 23000,
      "colors": ["Azul Francia", "Fucsia", "Rojo", "Negro", "Plateado", "Verde Esmeralda", "Dorado"],
      "image": "0401LU-Blusa Cruzada Lurex/DSC_0009.jpg",
      "description": "Brillo sofisticado que realza tu silueta. Diseño cruzado que estiliza y deslumbra."
    },
    {
      "sku": "0402LU",
      "category": "BLUSAS",
      "name": "Blusa Peplum",
      "fabric": "Lino",
      "sizes": ["8", "10", "12", "14"],
      "wholesalePrice": 16000,
      "retailPrice": 14000,
      "colors": ["Negro", "Azul Marino", "Beige", "Camel"],
      "image": "0402LU-Blusa Peplum/DSC_0001.jpg",
      "description": "El peplum que disimula y favorece. Frescura de lino con corte femenino irresistible."
    },
    {
      "sku": "0403PM",
      "category": "BLUSAS",
      "name": "Blusa Plumetí",
      "fabric": "Plumetí",
      "sizes": ["8", "10", "12", "14", "16"],
      "wholesalePrice": 12000,
      "retailPrice": 10000,
      "colors": ["Negro", "Rosa bebé", "Rosa viejo", "Beige"],
      "image": "0403PM-Blusa Plumetí/DSC_0001.jpg",
      "description": "Textura delicada y romántica. Perfecta para destacar con sutileza y feminidad."
    },
    {
      "sku": "0801FP",
      "category": "CAMISAS",
      "name": "Camisa Lazo Fibrana",
      "fabric": "Fibrana Poplin",
      "sizes": ["8", "10", "12", "14", "16"],
      "wholesalePrice": 20000,
      "retailPrice": 17000,
      "colors": ["Estampados"],
      "image": "0801FP-Camisa Lazo Fibrana/DSC_0001.jpg",
      "description": "El lazo que añade sofisticación a tu look. Tela liviana ideal para climas cálidos."
    },
    {
      "sku": "0802LY",
      "category": "CAMISAS",
      "name": "Camisa Lino Cey",
      "fabric": "Lino Cey",
      "sizes": ["6", "8", "10", "12", "14"],
      "wholesalePrice": 18000,
      "retailPrice": 16000,
      "colors": ["Negro", "Natural", "Beige", "Aero"],
      "image": "0802LY-Camisa Lino Sey/DSC_0001.jpg",
      "description": "Lino premium que respira frescura. Elegancia natural para tu día a día."
    },
    {
      "sku": "0803LI",
      "category": "CAMISAS",
      "name": "Camisa Andrea",
      "fabric": "Lino Spandex",
      "sizes": ["6", "8", "10", "12", "14"],
      "wholesalePrice": 15000,
      "retailPrice": 15000,
      "colors": ["Camel", "Coral", "Fucsia"],
      "image": "0803LI-Camisa Andrea/DSC_0001.jpg",
      "description": "Versatilidad con estilo. La camisa que va desde la oficina hasta la salida nocturna."
    },
    {
      "sku": "0804LI",
      "category": "CAMISAS",
      "name": "Camisa Aflora",
      "fabric": "Lino Spandex",
      "sizes": ["6", "8", "10", "12", "14"],
      "wholesalePrice": 23000,
      "retailPrice": 19000,
      "colors": ["Negro", "Blanco", "Azul Marino", "Rojo", "Camel", "Verde"],
      "image": "0804LI-Camisa Aflora/DSC_0001.jpg",
      "description": "Diseño que florece en cada ocasión. Comodidad y elegancia en perfecta armonía."
    },
    {
      "sku": "0902FI",
      "category": "CAMISOLAS",
      "name": "Camisola Fibrana Lisa",
      "fabric": "Fibrana Poplin",
      "sizes": ["6", "8", "12", "14"],
      "wholesalePrice": 7000,
      "retailPrice": 7000,
      "colors": ["Negro", "Beige"],
      "image": "0902FI-Camisola Fibrana Lisa/DSC_0001.jpg",
      "description": "Simplicidad sofisticada. La base perfecta para cualquier outfit veraniego."
    },
    {
      "sku": "0902FS",
      "category": "CAMISOLAS",
      "name": "Camisola Selva",
      "fabric": "Fibrana Poplin",
      "sizes": ["8", "10", "12", "14", "16"],
      "wholesalePrice": 15000,
      "retailPrice": 13000,
      "colors": ["Negro", "Beige", "Verde Oliva"],
      "image": "0902FS-Camisola Selva/DSC_0001.jpg",
      "description": "Estampado tropical que te transporta al paraíso. Frescura y estilo salvaje."
    },
    {
      "sku": "0902FC",
      "category": "CAMISOLAS",
      "name": "Camisola Cebra",
      "fabric": "Fibrana Poplin",
      "sizes": ["8", "10", "12", "14", "16"],
      "wholesalePrice": 15000,
      "retailPrice": 13000,
      "colors": ["Negro", "Blanco", "Beige"],
      "image": "0902FC-Camisola Cebra/DSC_0001.jpg",
      "description": "Animal print que marca tendencia. Atrévete a destacar con actitud salvaje."
    },
    {
      "sku": "0907LY",
      "category": "CAMISOLAS",
      "name": "Camisola Cey",
      "fabric": "Lino Cey",
      "sizes": ["8", "10", "12", "14", "16"],
      "wholesalePrice": 12000,
      "retailPrice": 10000,
      "colors": ["Negro", "Verde Oliva", "Beige", "Camel"],
      "image": "0907LY-Camisola Cey/DSC_0001.jpg",
      "description": "Liviandad que acaricia tu piel. El must-have de la temporada primavera-verano."
    },
    {
      "sku": "0908LY",
      "category": "CAMISOLAS",
      "name": "Camisola Cey Lazo Nudo",
      "fabric": "Lino Cey",
      "sizes": ["8", "10", "12", "14", "16"],
      "wholesalePrice": 13000,
      "retailPrice": 10000,
      "colors": ["Negro", "Crudo", "Rojo", "Azul", "Verde"],
      "image": "0908LY-Camisola Cey Lazo Nudo/DSC_0001.jpg",
      "description": "Detalle de lazo que conquista miradas. Feminidad en estado puro."
    },
    {
      "sku": "1000MD",
      "category": "CAMPERAS",
      "name": "Campera Modal",
      "fabric": "Modal con Lycra",
      "sizes": ["8", "10", "12", "14"],
      "wholesalePrice": 18000,
      "retailPrice": 15000,
      "colors": ["Negro", "Bordo", "Verde Militar", "Gris Topo"],
      "image": "1000MD-Campera Modal/DSC_0001.jpg",
      "description": "Abrigo liviano y súper suave. Tu compañera ideal para las noches frescas."
    },
    {
      "sku": "1005BE",
      "category": "CAMPERAS",
      "name": "Campera Bengalina",
      "fabric": "Bengalina Elastizada",
      "sizes": ["10", "12", "14"],
      "wholesalePrice": 23000,
      "retailPrice": 20000,
      "colors": ["Negro", "Gris Topo", "Azul Cielo", "Mostaza", "Chocolate"],
      "image": "1005BE-Campera Bengalina/DSC_0001.jpg",
      "description": "Estructura y confort en una sola prenda. El toque final para cualquier look."
    },
    {
      "sku": "1100MD",
      "category": "CAPRIS",
      "name": "Capri Modal",
      "fabric": "Modal con Lycra",
      "sizes": ["6", "8", "10", "12", "14", "16"],
      "wholesalePrice": 13000,
      "retailPrice": 10000,
      "colors": ["Negro", "Camel", "Azul Francia"],
      "image": "1100MD-Capri Modal/DSC_0001.jpg",
      "description": "Comodidad que no negocia con el estilo. Perfectos para moverte con libertad."
    },
    {
      "sku": "1102MQ",
      "category": "CAPRIS",
      "name": "Capri Morley Viscosa",
      "fabric": "Morley Viscosa",
      "sizes": ["8"],
      "wholesalePrice": 9000,
      "retailPrice": 9000,
      "colors": ["Camel", "Azul Francia"],
      "image": "1102MQ-Capri Morley Viscosa/DSC_0001.jpg",
      "description": "Textura morley que abraza tus curvas. Frescura y elasticidad incomparables."
    },
    {
      "sku": "1105LI",
      "category": "CAPRIS",
      "name": "Capri Lino Tribotón",
      "fabric": "Lino Spandex",
      "sizes": ["8", "10", "12", "14", "16"],
      "wholesalePrice": 18000,
      "retailPrice": 16000,
      "colors": ["Negro", "Camel", "Rojo", "Azul Marino"],
      "image": "1105LI-Capri Lino Tribotón/DSC_0001.jpg",
      "description": "Detalle de botones que enamora. Lino premium para las que saben de estilo."
    },
    {
      "sku": "1202CT",
      "category": "CHALECOS",
      "name": "Chaleco Crochet",
      "fabric": "Crochet",
      "sizes": ["12", "14", "16"],
      "wholesalePrice": 13000,
      "retailPrice": 10000,
      "colors": ["Negro", "Camel"],
      "image": "1202CT-Chaleco Crochet/DSC_0001.jpg",
      "description": "Artesanía que viste tu alma. Tejido boho que añade personalidad a cualquier look."
    },
    {
      "sku": "1203HW",
      "category": "CHALECOS",
      "name": "Chaleco Hawai",
      "fabric": "Hawai",
      "sizes": ["8", "10", "12", "14"],
      "wholesalePrice": 12000,
      "retailPrice": 10000,
      "colors": ["Negro", "Chocolate", "Rosa", "Crudo"],
      "image": "1203HW-Chaleco Hawai/DSC_0001.jpg",
      "description": "Versatilidad tropical para superponer con estilo. Ligero y muy combinable."
    },
    {
      "sku": "1500FI",
      "category": "KIMONOS",
      "name": "Kimono Fibrana",
      "fabric": "Fibrana Poplin",
      "sizes": ["8", "10", "12"],
      "wholesalePrice": 6000,
      "retailPrice": 6000,
      "colors": ["Estampados"],
      "image": "1500FI-Kimono Fibrana/DSC_0001.jpg",
      "description": "El toque bohemio que completa tu outfit. Fluidez y movimiento en cada paso."
    },
    {
      "sku": "1601LS",
      "category": "MONOS",
      "name": "Mono Lino",
      "fabric": "Lino",
      "sizes": ["12", "14"],
      "wholesalePrice": 20000,
      "retailPrice": 20000,
      "colors": ["Negro", "Verde Militar"],
      "image": "1601LS-Mono Lino/DSC_0001.jpg",
      "description": "Un solo paso y estás lista. Elegancia práctica para la mujer moderna."
    },
    {
      "sku": "1700FI",
      "category": "MUSCULOSAS",
      "name": "Musculosa Fibrana",
      "fabric": "Fibrana Poplin",
      "sizes": ["8", "12"],
      "wholesalePrice": 8000,
      "retailPrice": 8000,
      "colors": ["Negro", "Rojo", "Natural", "Camel", "Estampados"],
      "image": "1700FI-Musculosa Fibrana/DSC_0001.jpg",
      "description": "Básico esencial reinventado. Frescura y versatilidad para el verano."
    },
    {
      "sku": "1702MM",
      "category": "MUSCULOSAS",
      "name": "Musculosa Bretel Rip",
      "fabric": "Morley Rip",
      "sizes": ["8", "10", "12", "14"],
      "wholesalePrice": 10000,
      "retailPrice": 8000,
      "colors": ["Negro", "Gris", "Blanco"],
      "image": "1702MM-Musculosa Bretel Rip/DSC_0001.jpg",
      "description": "Breteles que estilizan. Textura acanalada que marca tendencia."
    },
    {
      "sku": "1704MM",
      "category": "MUSCULOSAS",
      "name": "Musculosa Rip",
      "fabric": "Morley Rip",
      "sizes": ["8", "10", "12", "14"],
      "wholesalePrice": 11000,
      "retailPrice": 9000,
      "colors": ["Negro", "Gris Topo", "Blanco"],
      "image": "1704MM-Musculosa Rip/DSC_0001.jpg",
      "description": "El básico premium que no puede faltar. Ajuste perfecto, comodidad total."
    },
    {
      "sku": "1705SX",
      "category": "MUSCULOSAS",
      "name": "Musculosa Buche",
      "fabric": "Lurex",
      "sizes": ["8", "10", "12", "14", "16"],
      "wholesalePrice": 17000,
      "retailPrice": 17000,
      "colors": ["Negro", "Beige", "Plateado", "Rojo", "Verde", "Fucsia"],
      "image": "1705SX-Musculosa Buche/DSC_0001.jpg",
      "description": "Brillo para las noches especiales. El detalle buche que enamora."
    },
    {
      "sku": "1900MD",
      "category": "PANTALONES",
      "name": "Pantalón Modal",
      "fabric": "Modal con Lycra",
      "sizes": ["10", "12"],
      "wholesalePrice": 9500,
      "retailPrice": 9500,
      "colors": ["Verde Militar", "Bordo"],
      "image": "1900MD-Pantalón Modal/DSC_0001.jpg",
      "description": "Suavidad extrema que acompaña cada movimiento. El pantalón que querrás usar siempre."
    },
    {
      "sku": "1901LU",
      "category": "PANTALONES",
      "name": "Palazzo Lúrex",
      "fabric": "Lúrex",
      "sizes": ["8", "10", "12", "14", "16"],
      "wholesalePrice": 26000,
      "retailPrice": 24000,
      "colors": ["Negro"],
      "image": "1901LU-Palazzo Lurex/DSC_0001.jpg",
      "description": "Palazzo de gala que deslumbra. Brillo y caída espectacular para tus eventos."
    },
    {
      "sku": "1901SF",
      "category": "PANTALONES",
      "name": "Palazzo Seda Fría",
      "fabric": "Seda Fría",
      "sizes": ["8", "10", "12", "14", "16"],
      "wholesalePrice": 23000,
      "retailPrice": 22000,
      "colors": ["Negro"],
      "image": "1901SF-Palazzo Seda Fría/DSC_0001.jpg",
      "description": "Fluidez de seda que acaricia. Elegancia atemporal para toda ocasión."
    },
    {
      "sku": "1901SB",
      "category": "PANTALONES",
      "name": "Palazzo Boreal",
      "fabric": "Seda Fría Haytiway",
      "sizes": ["8", "10", "12", "14", "16"],
      "wholesalePrice": 26000,
      "retailPrice": 23000,
      "colors": ["Estampados"],
      "image": "1901SB-Palazzo Boreal/DSC_0001.jpg",
      "description": "Estampado exclusivo que captura miradas. Caída impecable y diseño único."
    },
    {
      "sku": "1902MD",
      "category": "PANTALONES",
      "name": "Pantalón Recto Modal",
      "fabric": "Modal con Lycra",
      "sizes": ["6", "8", "10", "12", "14", "16"],
      "wholesalePrice": 15000,
      "retailPrice": 12000,
      "colors": ["Bordo", "Negro", "Verde Musgo"],
      "image": "1902MD-Pantalón Recto Modal/DSC_0001.jpg",
      "description": "Línea recta que alarga la silueta. Comodidad premium para el día a día."
    },
    {
      "sku": "1904FE",
      "category": "PANTALONES",
      "name": "Pantalón Fibrana Estampado",
      "fabric": "Fibrana Poplin",
      "sizes": ["5", "6", "8", "12", "14", "16"],
      "wholesalePrice": 12000,
      "retailPrice": 12000,
      "colors": ["Estampados"],
      "image": "1904FE-Pantalón Fibrana Estampado/DSC_0001.jpg",
      "description": "Estampados vibrantes que alegran tu look. Livianos y frescos para el calor."
    },
    {
      "sku": "1904FI",
      "category": "PANTALONES",
      "name": "Pantalón Fibrana Liso",
      "fabric": "Fibrana Poplin",
      "sizes": ["6", "12", "14", "16"],
      "wholesalePrice": 12000,
      "retailPrice": 12000,
      "colors": ["Negro", "Gris Topo"],
      "image": "1904FI-Pantalón Fibrana Liso/DSC_0001.jpg",
      "description": "La elegancia de lo simple. Versatilidad para combinar con todo tu guardarropa."
    },
    {
      "sku": "1905LI",
      "category": "PANTALONES",
      "name": "Pantalón Lazo Lino",
      "fabric": "Lino",
      "sizes": ["6", "8", "10", "12", "14", "16"],
      "wholesalePrice": 18000,
      "retailPrice": 16000,
      "colors": ["Negro", "Beige", "Azul Marino", "Verde Militar", "Rojo", "Chocolate"],
      "image": "1905LI-Pantalón Lazo Lino/DSC_0001.jpg",
      "description": "El lazo que define tu cintura. Lino natural para un look effortless chic."
    },
    {
      "sku": "1917MQ",
      "category": "PANTALONES",
      "name": "Pantalón Morley",
      "fabric": "Morley Viscosa",
      "sizes": ["8", "10", "12", "14", "16"],
      "wholesalePrice": 14000,
      "retailPrice": 14000,
      "colors": ["Camel", "Azul Francia"],
      "image": "1917MQ-Pantalón Morley/DSC_0001.jpg",
      "description": "Elasticidad y estilo en perfecta combinación. Tu segunda piel favorita."
    },
    {
      "sku": "1921BE",
      "category": "PANTALONES",
      "name": "Pantalón Bengalina",
      "fabric": "Bengalina Elastizada",
      "sizes": ["10", "12", "14"],
      "wholesalePrice": 23000,
      "retailPrice": 20000,
      "colors": ["Negro", "Camel", "Marrón", "Celeste", "Gris Topo"],
      "image": "1921BE-Pantalón Bengalina/DSC_0001.jpg",
      "description": "Sastrero reinventado para curvas reales. Elegancia que estiliza naturalmente."
    },
    {
      "sku": "1922HW",
      "category": "PANTALONES",
      "name": "Palazzo Hawai",
      "fabric": "Hawai",
      "sizes": ["8", "10", "12", "14", "16"],
      "wholesalePrice": 17000,
      "retailPrice": 14000,
      "colors": ["Negro", "Rosa", "Beige", "Camel"],
      "image": "1922HW-Palazzo Hawai/DSC_0001.jpg",
      "description": "Tela liviana con caída perfecta. El palazzo que vas a querer en todos los colores."
    },
    {
      "sku": "1923CA",
      "category": "PANTALONES",
      "name": "Palazzo Cey",
      "fabric": "Cey Airflow",
      "sizes": ["8", "10", "12", "14", "16"],
      "wholesalePrice": 17000,
      "retailPrice": 14000,
      "colors": ["Negro", "Beige", "Verde Oliva", "Rojo", "Chocolate"],
      "image": "1923CA-Palazzo Cey/DSC_0001.jpg",
      "description": "Airflow que respira frescura. Movimiento fluido que estiliza tu figura."
    },
    {
      "sku": "1923LI",
      "category": "PANTALONES",
      "name": "Palazzo Lino",
      "fabric": "Lino Spandex",
      "sizes": ["6", "8", "10", "12", "14", "16"],
      "wholesalePrice": 19000,
      "retailPrice": 16000,
      "colors": ["Negro", "Azul", "Verde"],
      "image": "1923LI-Palazzo Lino/DSC_0001.jpg",
      "description": "Lino premium con elasticidad. Frescura natural para los días más calurosos."
    },
    {
      "sku": "1923ST",
      "category": "PANTALONES",
      "name": "Palazzo Stella",
      "fabric": "Stella",
      "sizes": ["8", "10", "12", "14", "16"],
      "wholesalePrice": 14000,
      "retailPrice": 11000,
      "colors": ["Negro", "Beige", "Chocolate", "Bordo"],
      "image": "1923ST-Palazzo Stella/DSC_0001.jpg",
      "description": "Brilla como estrella. Palazzo con toque sutil de glamour cotidiano."
    },
    {
      "sku": "1923HW",
      "category": "PANTALONES",
      "name": "Palazzo Oxford Hawai",
      "fabric": "Hawai",
      "sizes": ["8", "10", "12", "14"],
      "wholesalePrice": 17000,
      "retailPrice": 14000,
      "colors": ["Negro", "Beige", "Camel"],
      "image": "1923HW-Palazzo Oxford Hawai/DSC_0001.jpg",
      "description": "Corte oxford que estiliza. Ideal para un look relajado pero sofisticado."
    },
    {
      "sku": "1923MQ",
      "category": "PANTALONES",
      "name": "Palazzo Oxford Morley",
      "fabric": "Morley Viscosa",
      "sizes": ["8", "10", "12", "14"],
      "wholesalePrice": 16000,
      "retailPrice": 14000,
      "colors": ["Verde Musgo", "Azul", "Negro"],
      "image": "1923MQ-Palazzo Oxford Morley/DSC_0001.jpg",
      "description": "Morley que abraza sin apretar. El balance perfecto entre comodidad y estilo."
    },
    {
      "sku": "1924CA",
      "category": "PANTALONES",
      "name": "Pantalón Recto Sastrero",
      "fabric": "Sastrero",
      "sizes": ["8", "10", "12", "14"],
      "wholesalePrice": 21000,
      "retailPrice": 18000,
      "colors": ["Negro", "Beige"],
      "image": "1924CA-Pantalón Recto Sastrero/DSC_0001.jpg",
      "description": "El pantalón de vestir que necesitás. Corte impecable para ocasiones formales."
    },
    {
      "sku": "2100SH",
      "category": "POLLERAS",
      "name": "Pollera Seda Fría",
      "fabric": "Seda Fría Haytiway",
      "sizes": ["12", "14", "16"],
      "wholesalePrice": 24000,
      "retailPrice": 21000,
      "colors": ["Estampados"],
      "image": "2100SH-Pollera Seda Fría/DSC_0001.jpg",
      "description": "Fluidez que danza con el viento. Estampados únicos para brillar."
    },
    {
      "sku": "2401SB",
      "category": "REMERAS",
      "name": "Remera Ana",
      "fabric": "Seda Fría Slinky c/Brillo",
      "sizes": ["8", "12", "14", "16"],
      "wholesalePrice": 15000,
      "retailPrice": 15000,
      "colors": ["Negro", "Rojo", "Azul Francia", "Azul Marino"],
      "image": "2401SB-Remera Ana/DSC_0001.jpg",
      "description": "Brillo sutil para tu día a día. Elegancia desenfadada que enamora."
    },
    {
      "sku": "2401MD",
      "category": "REMERAS",
      "name": "Remera Modal Jana",
      "fabric": "Modal con Lycra",
      "sizes": ["8", "10", "12", "14", "16"],
      "wholesalePrice": 17000,
      "retailPrice": 14000,
      "colors": ["Negro", "Camel", "Beige", "Azul Marino", "Verde Menta"],
      "image": "2401MD-Remera Modal Jana/DSC_0001.jpg",
      "description": "Modal premium que acaricia tu piel. El básico elevado que mereces."
    },
    {
      "sku": "2401MV",
      "category": "REMERAS",
      "name": "Remera Dina",
      "fabric": "Modal Viscosa",
      "sizes": ["8", "10", "12", "14"],
      "wholesalePrice": 12000,
      "retailPrice": 12000,
      "colors": ["Negro", "Camel", "Coral", "Verde Botella", "Azul Francia", "Verde Militar", "Rojo Tomate"],
      "image": "2401MV-Remera Dina/DSC_0001.jpg",
      "description": "Colores vibrantes para personalidades auténticas. Suavidad incomparable."
    },
    {
      "sku": "2401AL",
      "category": "REMERAS",
      "name": "Remera Algodón",
      "fabric": "Algodón",
      "sizes": ["8", "10", "12", "14", "16"],
      "wholesalePrice": 14000,
      "retailPrice": 12000,
      "colors": ["Negro", "Beige", "Amarillo", "Rosa"],
      "image": "2401AL-Remera Algodón/DSC_0001.jpg",
      "description": "Algodón natural que respira. El clásico que nunca falla."
    },
    {
      "sku": "2401MQ",
      "category": "REMERAS",
      "name": "Remera Morley Viscosa",
      "fabric": "Morley Viscosa",
      "sizes": ["8", "10", "12", "14", "16"],
      "wholesalePrice": 14000,
      "retailPrice": 12000,
      "colors": ["Marrón", "Verde Inglés", "Bordo", "Crudo", "Negro"],
      "image": "2401MQ-Remera Morley Viscosa/DSC_0001.jpg",
      "description": "Textura morley con caída perfecta. Estilo relajado con mucha onda."
    },
    {
      "sku": "2404LU",
      "category": "REMERAS",
      "name": "Remera Bianca",
      "fabric": "Lúrex",
      "sizes": ["6"],
      "wholesalePrice": 10000,
      "retailPrice": 10000,
      "colors": ["Dorado"],
      "image": "2404LU-Remera Bianca/DSC_0001.jpg",
      "description": "Brillo dorado para ocasiones únicas. Deslumbrá en cada evento."
    },
    {
      "sku": "2404MQ",
      "category": "REMERAS",
      "name": "Remera Leila",
      "fabric": "Modal Viscosa",
      "sizes": ["8", "10", "12", "14", "16"],
      "wholesalePrice": 12000,
      "retailPrice": 12000,
      "colors": ["Negro", "Azul Francia", "Gris Melange", "Verde Agua", "Coral", "Gris Topo", "Verde Militar"],
      "image": "2404MQ-Remera Leila/DSC_0001.jpg",
      "description": "Versatilidad en estado puro. Perfecta para combinar con todo."
    },
    {
      "sku": "2404MZ",
      "category": "REMERAS",
      "name": "Remera Lunar",
      "fabric": "Modal Viscosa",
      "sizes": ["8", "10", "12", "14", "16"],
      "wholesalePrice": 19000,
      "retailPrice": 16000,
      "colors": ["Negro", "Verde Menta", "Beige", "Rosa"],
      "image": "2404MZ-Remera Lunar/DSC_0001.jpg",
      "description": "Detalle lunar que añade dulzura. Diseño único para destacar."
    },
    {
      "sku": "2404MV",
      "category": "REMERAS",
      "name": "Remera Modal Viscosa",
      "fabric": "Modal Viscosa",
      "sizes": ["8", "10", "12", "14", "16"],
      "wholesalePrice": 14000,
      "retailPrice": 12000,
      "colors": ["Negro", "Azul Marino", "Verde Menta", "Beige", "Natural"],
      "image": "2404MV-Remera Modal Viscosa/DSC_0001.jpg",
      "description": "La combinación perfecta de suavidad y durabilidad. Tu remera de cada día."
    },
    {
      "sku": "2404SF",
      "category": "REMERAS",
      "name": "Remera Seda Fría V",
      "fabric": "Seda Fría",
      "sizes": ["6", "8"],
      "wholesalePrice": 10000,
      "retailPrice": 10000,
      "colors": ["Negro", "Blanco"],
      "image": "2404SF-Remera Seda Fría V/DSC_0001.jpg",
      "description": "Escote V que estiliza. Frescura de seda para el verano."
    },
    {
      "sku": "2405MV",
      "category": "REMERAS",
      "name": "Remera Modal 3/4",
      "fabric": "Modal Viscosa",
      "sizes": ["8", "10", "12", "14", "16"],
      "wholesalePrice": 17000,
      "retailPrice": 17000,
      "colors": ["Negro", "Bordo", "Verde Militar", "Azul", "Natural"],
      "image": "2405MV-Remera Modal 3-4/DSC_0001.jpg",
      "description": "Manga 3/4 para entretiempo. Elegancia cómoda todo el año."
    },
    {
      "sku": "2407MQ",
      "category": "REMERAS",
      "name": "Remera Nora",
      "fabric": "Morley Viscosa",
      "sizes": ["6", "12"],
      "wholesalePrice": 7000,
      "retailPrice": 7000,
      "colors": ["Natural", "Mostaza", "Azul Francia", "Rosa", "Gris Melange", "Gris Topo"],
      "image": "2407MQ-Remera Nora/DSC_0001.jpg",
      "description": "Precio amigable, calidad premium. El básico que no puede faltar."
    },
    {
      "sku": "2409MQ",
      "category": "REMERAS",
      "name": "Remera Rubí",
      "fabric": "Morley Viscosa",
      "sizes": ["6"],
      "wholesalePrice": 5000,
      "retailPrice": 5000,
      "colors": ["Negro", "Gris Topo"],
      "image": "2409MQ-Remera Rubí/DSC_0001.jpg",
      "description": "Simplicidad brillante. El básico esencial a precio irresistible."
    },
    {
      "sku": "2416BR",
      "category": "REMERAS",
      "name": "Remera Broderie",
      "fabric": "Broderie",
      "sizes": ["8", "10", "12", "14", "16"],
      "wholesalePrice": 15000,
      "retailPrice": 12000,
      "colors": ["Negro", "Camel", "Beige"],
      "image": "2416BR-Remera Broderie/DSC_0001.jpg",
      "description": "Bordado artesanal que enamora. Feminidad en cada detalle."
    },
    {
      "sku": "2416MV",
      "category": "REMERAS",
      "name": "Remera Estampada",
      "fabric": "Modal Viscosa",
      "sizes": ["8", "10", "12", "14", "16"],
      "wholesalePrice": 19000,
      "retailPrice": 16000,
      "colors": ["Rojo", "Negro", "Verde Menta", "Azul Marino"],
      "image": "2416MV-Remera Estampada/DSC_0001.jpg",
      "description": "Estampados exclusivos que te hacen única. Diseño y calidad premium."
    },
    {
      "sku": "2416HW",
      "category": "REMERAS",
      "name": "Remera Hawai",
      "fabric": "Hawai",
      "sizes": ["8", "10", "12", "14", "16"],
      "wholesalePrice": 12000,
      "retailPrice": 10000,
      "colors": ["Negro", "Beige", "Rosa", "Camel"],
      "image": "2416HW-Remera Hawai/DSC_0001.jpg",
      "description": "Frescura tropical para tu día a día. Liviandad y estilo sin esfuerzo."
    },
    {
      "sku": "2802LU",
      "category": "SAQUITOS",
      "name": "Saquito Lúrex",
      "fabric": "Lúrex",
      "sizes": ["8", "10", "12", "14"],
      "wholesalePrice": 26000,
      "retailPrice": 24000,
      "colors": ["Negro"],
      "image": "2802LU-Saquito Lurex/DSC_0001.jpg",
      "description": "Brillo que abriga con glamour. Perfecto para noches especiales."
    },
    {
      "sku": "2802SF",
      "category": "SAQUITOS",
      "name": "Spolverino Seda Fría",
      "fabric": "Seda Fría",
      "sizes": ["8", "10", "12"],
      "wholesalePrice": 16000,
      "retailPrice": 16000,
      "colors": ["Negro"],
      "image": "2802SF-Spolverino Seda Fría/DSC_0001.jpg",
      "description": "Elegancia fluida para superponer. El toque final de sofisticación."
    },
    {
      "sku": "2900MD",
      "category": "SHORTS",
      "name": "Short Modal",
      "fabric": "Modal con Lycra",
      "sizes": ["6", "8", "10", "12", "14", "16"],
      "wholesalePrice": 11000,
      "retailPrice": 8000,
      "colors": ["Negro", "Uva", "Camel", "Gris Topo", "Azul Marino", "Verde Militar"],
      "image": "2900MD-Short Modal/DSC_0001.jpg",
      "description": "Comodidad veraniega en estado puro. Suavidad modal para tus curvas."
    },
    {
      "sku": "2903FI",
      "category": "SHORTS",
      "name": "Short Fibrana",
      "fabric": "Fibrana Poplin",
      "sizes": ["14"],
      "wholesalePrice": 8000,
      "retailPrice": 8000,
      "colors": ["Estampados"],
      "image": "2903FI-Short Fibrana/DSC_0001.jpg",
      "description": "Estampados vibrantes para el verano. Frescura y estilo playero."
    },
    {
      "sku": "2903HW",
      "category": "SHORTS",
      "name": "Short Hawai",
      "fabric": "Hawai",
      "sizes": ["8", "10", "12", "14", "16"],
      "wholesalePrice": 11000,
      "retailPrice": 8000,
      "colors": ["Negro", "Crudo", "Marrón"],
      "image": "2903HW-Short Hawai/DSC_0001.jpg",
      "description": "Liviandad tropical para días calurosos. Movimiento libre y cómodo."
    },
    {
      "sku": "2909LI",
      "category": "SHORTS",
      "name": "Short Lino",
      "fabric": "Lino Spandex",
      "sizes": ["12", "14", "16"],
      "wholesalePrice": 14000,
      "retailPrice": 11000,
      "colors": ["Negro", "Estampados"],
      "image": "2909LI-Short Lino/DSC_0001.jpg",
      "description": "Lino premium para el verano. Naturaleza y confort en perfecta armonía."
    },
    {
      "sku": "2910CA",
      "category": "SHORTS",
      "name": "Short Pollera Cey",
      "fabric": "Cey",
      "sizes": ["8", "10", "12", "14", "16"],
      "wholesalePrice": 8000,
      "retailPrice": 8000,
      "colors": ["Negro", "Celeste", "Beige", "Rojo", "Azul Marino"],
      "image": "2910CA-Short Pollera Cey/DSC_0001.jpg",
      "description": "Lo mejor de dos mundos: short y pollera. Feminidad con libertad de movimiento."
    },
    {
      "sku": "2910LI",
      "category": "SHORTS",
      "name": "Bermuda Lino Tribotón",
      "fabric": "Lino",
      "sizes": ["8", "10", "12", "14", "16"],
      "wholesalePrice": 16000,
      "retailPrice": 14000,
      "colors": ["Negro", "Rojo", "Marrón", "Azul Marino"],
      "image": "2910LI-Bermuda Lino Tribotón/DSC_0001.jpg",
      "description": "Bermuda elegante con detalle de botones. Versatilidad para cualquier ocasión."
    },
    {
      "sku": "3100SL",
      "category": "VESTIDOS",
      "name": "Vestido Sabrina",
      "fabric": "Seda Fría Slinky",
      "sizes": ["8", "10", "12", "14", "16"],
      "wholesalePrice": 20000,
      "retailPrice": 20000,
      "colors": ["Negro", "Estampados"],
      "image": "3100SL-Vestido Sabrina/DSC_0001.jpg",
      "description": "Elegancia que fluye. El vestido que te hará sentir espectacular."
    },
    {
      "sku": "3102FI",
      "category": "VESTIDOS",
      "name": "Vestido con Volado",
      "fabric": "Fibrana",
      "sizes": ["8", "10", "12", "14", "16"],
      "wholesalePrice": 23000,
      "retailPrice": 19000,
      "colors": ["Estampados"],
      "image": "3102FI-Vestido con Volado/DSC_0001.jpg",
      "description": "Volados que danzan con cada paso. Romanticismo y frescura en un solo vestido."
    },
    {
      "sku": "3106MY",
      "category": "VESTIDOS",
      "name": "Vestido Morley",
      "fabric": "Morley Algodón",
      "sizes": ["6", "8", "10"],
      "wholesalePrice": 12000,
      "retailPrice": 12000,
      "colors": ["Fucsia", "Gris Topo"],
      "image": "3106MY-Vestido Morley/DSC_0001.jpg",
      "description": "Comodidad stretch que abraza tus curvas. Casual y chic a la vez."
    },
    {
      "sku": "3107CR",
      "category": "VESTIDOS",
      "name": "Vestido Camisero",
      "fabric": "Creep",
      "sizes": ["6", "8"],
      "wholesalePrice": 7000,
      "retailPrice": 7000,
      "colors": ["Negro", "Blanco", "Rosa"],
      "image": "3107CR-Vestido Camisero/DSC_0001.jpg",
      "description": "El clásico camisero reinventado. Versatilidad para oficina y paseo."
    },
    {
      "sku": "3109CA",
      "category": "VESTIDOS",
      "name": "Vestido Cey",
      "fabric": "Cey Airflow",
      "sizes": ["8", "10", "12", "14"],
      "wholesalePrice": 20000,
      "retailPrice": 17000,
      "colors": ["Negro", "Beige", "Verde"],
      "image": "3109CA-Vestido Cey/DSC_0001.jpg",
      "description": "Airflow que respira frescura. Caída impecable para lucir espectacular."
    },
    {
      "sku": "3110FI",
      "category": "VESTIDOS",
      "name": "Solero Fibrana",
      "fabric": "Fibrana Poplin",
      "sizes": ["6", "8", "12", "14", "16"],
      "wholesalePrice": 12000,
      "retailPrice": 12000,
      "colors": ["Estampados"],
      "image": "3110FI-Solero Fibrana/DSC_0001.jpg",
      "description": "Frescura veraniega que enamora. Estampados únicos para brillar bajo el sol."
    },
    {
      "sku": "3110SF",
      "category": "VESTIDOS",
      "name": "Solero Seda Fría",
      "fabric": "Seda Fría Slinky",
      "sizes": ["6", "8", "10", "12"],
      "wholesalePrice": 20000,
      "retailPrice": 20000,
      "colors": ["Negro"],
      "image": "3110SF-Solero Seda Fría/DSC_0001.jpg",
      "description": "Elegancia minimalista para el verano. Simplicidad que impacta."
    },
    {
      "sku": "3112CR",
      "category": "VESTIDOS",
      "name": "Vestido Bretel Creep",
      "fabric": "Creep",
      "sizes": ["6", "8"],
      "wholesalePrice": 10000,
      "retailPrice": 10000,
      "colors": ["Negro", "Camel"],
      "image": "3112CR-Vestido Bretel Creep/DSC_0001.jpg",
      "description": "Breteles que estilizan. Sensualidad sutil para ocasiones especiales."
    },
    {
      "sku": "3113AL",
      "category": "VESTIDOS",
      "name": "Vestido Hindú",
      "fabric": "Algodón",
      "sizes": ["Talle único 6"],
      "wholesalePrice": 24000,
      "retailPrice": 22000,
      "colors": ["Estampados"],
      "image": "3113AL-Vestido Hindú/DSC_0001.jpg",
      "description": "Espíritu bohemio que libera. Estampados artesanales únicos."
    },
    {
      "sku": "3115FI",
      "category": "VESTIDOS",
      "name": "Batón Fibrana",
      "fabric": "Fibrana",
      "sizes": ["14", "16"],
      "wholesalePrice": 14000,
      "retailPrice": 14000,
      "colors": ["Estampados"],
      "image": "3115FI-Batón Fibrana/DSC_0001.jpg",
      "description": "Comodidad de casa con estilo de calle. El batón más chic."
    },
    {
      "sku": "3116FI",
      "category": "VESTIDOS",
      "name": "Vestido Flor",
      "fabric": "Fibrana",
      "sizes": ["6", "8"],
      "wholesalePrice": 8000,
      "retailPrice": 8000,
      "colors": ["Negro", "Beige"],
      "image": "3116FI-Vestido Flor/DSC_0001.jpg",
      "description": "Detalle floral que enamora. Dulzura y feminidad en cada pétalo."
    },
    {
      "sku": "3118LE",
      "category": "VESTIDOS",
      "name": "Vestido Isabel",
      "fabric": "Lino Estampado",
      "sizes": ["10", "12", "14", "16"],
      "wholesalePrice": 15000,
      "retailPrice": 15000,
      "colors": ["Estampados"],
      "image": "3118LE-Vestido Isabel/DSC_0001.jpg",
      "description": "Lino estampado para ocasiones especiales. Naturaleza y arte en tu vestir."
    },
    {
      "sku": "3118LI",
      "category": "VESTIDOS",
      "name": "Vestido Lino",
      "fabric": "Lino Spandex",
      "sizes": ["10", "14"],
      "wholesalePrice": 12000,
      "retailPrice": 12000,
      "colors": ["Verde Limón", "Verde Manzana"],
      "image": "3118LI-Vestido Lino/DSC_0001.jpg",
      "description": "Colores vibrantes que refrescan. Lino premium para el verano."
    },
    {
      "sku": "3121MV",
      "category": "VESTIDOS",
      "name": "Vestido Vivi",
      "fabric": "Modal Viscosa",
      "sizes": ["8"],
      "wholesalePrice": 12000,
      "retailPrice": 12000,
      "colors": ["Camel"],
      "image": "3121MV-Vestido Vivi/DSC_0001.jpg",
      "description": "Suavidad modal que abraza. Diseño envolvente que favorece."
    },
    {
      "sku": "3122MX",
      "category": "VESTIDOS",
      "name": "Vestido Renata",
      "fabric": "Morley Lúrex",
      "sizes": ["8", "10", "12"],
      "wholesalePrice": 13000,
      "retailPrice": 13000,
      "colors": ["Negro", "Rosa Viejo", "Violeta", "Rojo", "Beige"],
      "image": "3122MX-Vestido Renata/DSC_0001.jpg",
      "description": "Brillo sutil para momentos especiales. Elegancia que no pasa desapercibida."
    },
    {
      "sku": "3123MX",
      "category": "VESTIDOS",
      "name": "Solero Coraline",
      "fabric": "Morley Lúrex",
      "sizes": ["8", "10", "12", "14"],
      "wholesalePrice": 12000,
      "retailPrice": 12000,
      "colors": ["Negro", "Rosa Palo", "Violeta", "Rojo", "Fucsia"],
      "image": "3123MX-Solero Coraline/DSC_0001.jpg",
      "description": "Romanticismo con brillo. El solero perfecto para atardeceres de verano."
    },
    {
      "sku": "3124AL",
      "category": "VESTIDOS",
      "name": "Solero Hindú",
      "fabric": "Algodón",
      "sizes": ["Talle único 6"],
      "wholesalePrice": 20000,
      "retailPrice": 20000,
      "colors": ["Crudo", "Turquesa", "Azul", "Bordo", "Beige", "Naranja"],
      "image": "3124AL-Solero Hindú/DSC_0001.jpg",
      "description": "Alma libre en algodón puro. Estampados que cuentan historias."
    },
    {
      "sku": "3124CY",
      "category": "VESTIDOS",
      "name": "Solero Cey",
      "fabric": "Cey Airflow",
      "sizes": ["8", "10", "12", "14"],
      "wholesalePrice": 17000,
      "retailPrice": 15000,
      "colors": ["Negro", "Verde Menta", "Beige"],
      "image": "3124CY-Solero Cey/DSC_0001.jpg",
      "description": "Airflow que respira contigo. Frescura y movimiento para el verano."
    },
    {
      "sku": "3125CY",
      "category": "VESTIDOS",
      "name": "Vestido Cey Scarlett",
      "fabric": "Cey",
      "sizes": ["12", "14", "16"],
      "wholesalePrice": 20000,
      "retailPrice": 17000,
      "colors": ["Negro", "Rojo", "Celeste"],
      "image": "3125CY-Vestido Cey Scarlett/DSC_0001.jpg",
      "description": "Pasión y elegancia en un vestido. Para las que saben destacar."
    },
    {
      "sku": "3126CY",
      "category": "VESTIDOS",
      "name": "Solero Cey Broderie",
      "fabric": "Cey Broderie",
      "sizes": ["8", "10", "12", "14", "16"],
      "wholesalePrice": 20000,
      "retailPrice": 17000,
      "colors": ["Negro", "Beige", "Celeste"],
      "image": "3126CY-Solero Cey Broderie/DSC_0001.jpg",
      "description": "Bordado artesanal que enamora. Delicadeza y frescura para el verano."
    }
  ],
  "categories": [
    "BABUCHAS",
    "BLAZERS",
    "BLUSAS",
    "CAMISAS",
    "CAMISOLAS",
    "CAMPERAS",
    "CAPRIS",
    "CHALECOS",
    "KIMONOS",
    "MONOS",
    "MUSCULOSAS",
    "PANTALONES",
    "POLLERAS",
    "REMERAS",
    "SAQUITOS",
    "SHORTS",
    "VESTIDOS"
  ]
}






